toit
